{
  "id":2,
  "name":"Mortgage",
  "description": "Charge registration service to support an easy, quick and secure fully online secured loan (mortgage) experience for homeowners",
  "programme": "Digital",
  "theme": "Digital",
  "location": "Plymouth",
  "phase":"beta",
  "phase_modifier":"private",
  "sro":"Eddie Davies",
  "service_man":"Ian Howe",
  "scrum_master":"Andrew Bartlett",
  "prototype":"https://charges-prototype-ci.herokuapp.com/",
  "phase-history":{
    "discovery": [
      {"label":"", "date": ""},
      {"label":"", "date": ""}
    ],
    "alpha": [
      {"label":"", "date": ""},
      {"label":"", "date": ""}
    ],
    "beta": [
       {"label":"private started", "date": "9 February 2016"},
       {"label":"public start predicted", "date": "31 March 2016"}
    ]
  },
  "facing":"user",
  "priority":"High"
}